palindrome_helper/__init__.py
palindrome_helper/palindrome.py
palindrome_helper-0.1.0.dist-info/licenses/LICENCE
tests/__init__.py
tests/test_palindrome.py
palindrome_helper-0.1.0.dist-info/METADATA
palindrome_helper-0.1.0.dist-info/WHEEL
palindrome_helper-0.1.0.dist-info/top_level.txt
palindrome_helper-0.1.0.dist-info/RECORD
