Metadata-Version: 2.4
Name: palindrome_helper
Version: 0.1.0
Summary: A helper file is simple up your palindrome check
Author: vishva R
Author-email: vishvaiioe@gmail.com
Classifier: Programming Language :: Python :: 3
Classifier: License :: OSI Approved :: MIT License
Classifier: Operating System :: OS Independent
License-File: LICENCE
Dynamic: author
Dynamic: author-email
Dynamic: classifier
Dynamic: description
Dynamic: description-content-type
Dynamic: license-file
Dynamic: summary
